LICENSE
MANIFEST.in
README.rst
setup.py
version.log
dict_minimize/__init__.py
dict_minimize/jax_api.py
dict_minimize/numpy_api.py
dict_minimize/tensorflow_api.py
dict_minimize/torch_api.py
dict_minimize.egg-info/PKG-INFO
dict_minimize.egg-info/SOURCES.txt
dict_minimize.egg-info/dependency_links.txt
dict_minimize.egg-info/requires.txt
dict_minimize.egg-info/top_level.txt
dict_minimize/core/__init__.py
dict_minimize/core/_scipy.py
requirements/base.in
requirements/frameworks.in
requirements/tests.in