Metadata-Version: 2.1
Name: dict-minimize
Version: 0.0.3
Summary: Access scipy optimizers from your favorite deep learning framework.
Home-page: https://github.com/twitter/dict_minimize/
Author: Ryan Turner
Author-email: rdturnermtl@github.com
License: Apache v2
Platform: any
Requires-Python: >=3.6
Provides-Extra: framework
Provides-Extra: test
